voseador/__init__.py
voseador/a.py
voseador/voseador.py
voseador-0.1.1.dist-info/METADATA
voseador-0.1.1.dist-info/WHEEL
voseador-0.1.1.dist-info/licenses/LICENSE
voseador-0.1.1.dist-info/RECORD
