Metadata-Version: 2.1
Name: voseador
Version: 0.1.1
Summary: A tiny python package to conjugate spanish verbs with 'voseo' (using vos instead of tu). Seamless integration with the verbecc spanish conjugator.
Project-URL: Github, https://github.com/CoolRobotsAndStuff/voseador
Author-email: Alejandro Mohnblatt <aledeum.saf@gmail.com>
License: MIT License
License-File: LICENSE
Keywords: argentina,argentinizador,castellano,chile,conjugación,conjugador,conjugation,conjugator,español,linguistics,lingüística,paraguay,spanish,uruguay,verbos,verbs,vos,voseador,voseo
Classifier: License :: OSI Approved :: MIT License
Classifier: Natural Language :: Spanish
Classifier: Operating System :: OS Independent
Classifier: Programming Language :: Python :: 3
Classifier: Topic :: Text Processing
Classifier: Topic :: Text Processing :: Linguistic
Requires-Python: >=3.7
Requires-Dist: unidecode>=1.3.6
